oli/__init__.py
oli/tracing/__init__.py
oli/tracing/client.py
oli/tracing/tracing.py
oli_tracing-0.4.7.dist-info/METADATA
oli_tracing-0.4.7.dist-info/WHEEL
oli_tracing-0.4.7.dist-info/RECORD
